VUDA/__init__.py
VUDA/io/__init__.py
VUDA/io/dataloader.py
VUDA/io/errors.py
VUDA/io/io_utils.py
VUDA/io/loadbinary.py
VUDA-0.0.13.dist-info/METADATA
VUDA-0.0.13.dist-info/WHEEL
VUDA-0.0.13.dist-info/top_level.txt
VUDA-0.0.13.dist-info/RECORD
